r00docker/__init__.py
r00docker/core.py
r00docker/helpers/__init__.py
r00docker/helpers/exceptions.py
r00docker-0.1.1.dist-info/METADATA
r00docker-0.1.1.dist-info/WHEEL
r00docker-0.1.1.dist-info/RECORD
