Metadata-Version: 2.4
Name: r00docker
Version: 0.1.1
Requires-Python: >=3.10
Requires-Dist: docker==7.1.0
Requires-Dist: r00logger
Requires-Dist: r00secret
